{
  "31eba8fe40243a3e0e029a8b9949d756": {
    "pushed_date": "2026-06-04",
    "pre_pushed": true,
    "sim_result": {
      "home_win_pct": 47.1,
      "away_win_pct": 42.0,
      "draw_pct": null,
      "over_pct": 52.0,
      "under_pct": 48.0,
      "home_cover_pct": 36.6,
      "spread_line": -1.214,
      "total_line": 7.603,
      "top5_scores": [
        [
          4,
          4,
          2.5
        ],
        [
          4,
          3,
          2.4
        ],
        [
          3,
          4,
          2.3
        ],
        [
          5,
          3,
          2.3
        ],
        [
          5,
          4,
          2.3
        ]
      ],
      "home_mean": 3.9,
      "away_mean": 3.7,
      "pred_mode": "📐 規則模擬",
      "error": null,
      "has_value": true,
      "value_team": "away",
      "value_edge": 7.6,
      "home_edge": -18.5,
      "away_edge": 7.6,
      "kelly_pct": 9.6,
      "confidence": "🟢 高",
      "spread_line_txt": "Phillies +1.214｜覆蓋率 36.6%",
      "market_home_prob": 65.6,
      "market_away_prob": 34.4,
      "home_team": "Philadelphia Phillies",
      "away_team": "San Diego Padres",
      "home_short": "Phillies",
      "away_short": "Padres"
    }
  },
  "3ca053166f16be8d40c5adfe1a2bd8aa": {
    "pushed_date": "2026-06-04",
    "pre_pushed": true,
    "sim_result": {
      "home_win_pct": 43.2,
      "away_win_pct": 46.1,
      "draw_pct": null,
      "over_pct": 46.1,
      "under_pct": 53.9,
      "home_cover_pct": 33.0,
      "spread_line": -1.107,
      "total_line": 9.155,
      "top5_scores": [
        [
          5,
          5,
          2.5
        ],
        [
          4,
          5,
          2.5
        ],
        [
          4,
          4,
          2.4
        ],
        [
          5,
          4,
          2.4
        ],
        [
          4,
          6,
          2.2
        ]
      ],
      "home_mean": 4.5,
      "away_mean": 4.7,
      "pred_mode": "📐 規則模擬",
      "error": null,
      "has_value": false,
      "value_team": "",
      "value_edge": 0.9,
      "home_edge": 0.9,
      "away_edge": -11.6,
      "kelly_pct": 3.6,
      "confidence": "🟢 高",
      "spread_line_txt": "Sox +1.107｜覆蓋率 33.0%",
      "market_home_prob": 42.3,
      "market_away_prob": 57.7,
      "home_team": "Boston Red Sox",
      "away_team": "Baltimore Orioles",
      "home_short": "Sox",
      "away_short": "Orioles"
    }
  },
  "859f56a081b813c2f16240bc2687f241": {
    "pushed_date": "2026-06-04",
    "pre_pushed": true,
    "sim_result": {
      "home_win_pct": 43.2,
      "away_win_pct": 45.6,
      "draw_pct": null,
      "over_pct": 55.2,
      "under_pct": 44.8,
      "home_cover_pct": 32.8,
      "spread_line": -1.107,
      "total_line": 6.828,
      "top5_scores": [
        [
          3,
          4,
          2.5
        ],
        [
          3,
          3,
          2.4
        ],
        [
          4,
          3,
          2.4
        ],
        [
          4,
          4,
          2.4
        ],
        [
          2,
          4,
          2.2
        ]
      ],
      "home_mean": 3.4,
      "away_mean": 3.5,
      "pred_mode": "📐 規則模擬",
      "error": null,
      "has_value": false,
      "value_team": "",
      "value_edge": 1.0,
      "home_edge": 1.0,
      "away_edge": -12.2,
      "kelly_pct": 2.9,
      "confidence": "🟢 高",
      "spread_line_txt": "Yankees +1.107｜覆蓋率 32.8%",
      "market_home_prob": 42.2,
      "market_away_prob": 57.8,
      "home_team": "New York Yankees",
      "away_team": "Cleveland Guardians",
      "home_short": "Yankees",
      "away_short": "Guardians"
    }
  },
  "682766eb5df9e22bd3689cd7ae59899b": {
    "pushed_date": "2026-06-04",
    "pre_pushed": true,
    "sim_result": {
      "home_win_pct": 46.2,
      "away_win_pct": 43.1,
      "draw_pct": null,
      "over_pct": 52.1,
      "under_pct": 47.9,
      "home_cover_pct": 35.8,
      "spread_line": -1.036,
      "total_line": 8.655,
      "top5_scores": [
        [
          4,
          4,
          2.5
        ],
        [
          5,
          4,
          2.5
        ],
        [
          4,
          5,
          2.4
        ],
        [
          5,
          5,
          2.3
        ],
        [
          5,
          3,
          2.2
        ]
      ],
      "home_mean": 4.4,
      "away_mean": 4.2,
      "pred_mode": "📐 規則模擬",
      "error": null,
      "has_value": false,
      "value_team": "",
      "value_edge": 1.7,
      "home_edge": -12.4,
      "away_edge": 1.7,
      "kelly_pct": 0.0,
      "confidence": "🟢 高",
      "spread_line_txt": "Reds +1.036｜覆蓋率 35.8%",
      "market_home_prob": 58.6,
      "market_away_prob": 41.4,
      "home_team": "Cincinnati Reds",
      "away_team": "Kansas City Royals",
      "home_short": "Reds",
      "away_short": "Royals"
    }
  },
  "7440e18762df663a2c7e8fe443772540": {
    "pushed_date": "2026-06-04",
    "pre_pushed": true,
    "sim_result": {
      "home_win_pct": 45.8,
      "away_win_pct": 43.4,
      "draw_pct": null,
      "over_pct": 50.1,
      "under_pct": 49.9,
      "home_cover_pct": 35.4,
      "spread_line": -1.093,
      "total_line": 8.482,
      "top5_scores": [
        [
          4,
          4,
          2.5
        ],
        [
          5,
          4,
          2.4
        ],
        [
          4,
          5,
          2.4
        ],
        [
          5,
          5,
          2.3
        ],
        [
          4,
          3,
          2.2
        ]
      ],
      "home_mean": 4.3,
      "away_mean": 4.2,
      "pred_mode": "📐 規則模擬",
      "error": null,
      "has_value": false,
      "value_team": "",
      "value_edge": 0.6,
      "home_edge": -11.4,
      "away_edge": 0.6,
      "kelly_pct": 0.0,
      "confidence": "🟢 高",
      "spread_line_txt": "Braves +1.093｜覆蓋率 35.4%",
      "market_home_prob": 57.1,
      "market_away_prob": 42.9,
      "home_team": "Atlanta Braves",
      "away_team": "Toronto Blue Jays",
      "home_short": "Braves",
      "away_short": "Jays"
    }
  },
  "2b93a316b12e1dddfcb752bed7aa43d6": {
    "pushed_date": "2026-06-04",
    "pre_pushed": true,
    "sim_result": {
      "home_win_pct": 46.0,
      "away_win_pct": 43.3,
      "draw_pct": null,
      "over_pct": 47.3,
      "under_pct": 52.7,
      "home_cover_pct": 35.5,
      "spread_line": -1.077,
      "total_line": 8.25,
      "top5_scores": [
        [
          4,
          4,
          2.5
        ],
        [
          5,
          4,
          2.4
        ],
        [
          4,
          5,
          2.3
        ],
        [
          4,
          3,
          2.3
        ],
        [
          3,
          4,
          2.3
        ]
      ],
      "home_mean": 4.2,
      "away_mean": 4.1,
      "pred_mode": "📐 規則模擬",
      "error": null,
      "has_value": false,
      "value_team": "",
      "value_edge": 0.9,
      "home_edge": -11.6,
      "away_edge": 0.9,
      "kelly_pct": 0.0,
      "confidence": "🟢 高",
      "spread_line_txt": "Brewers +1.077｜覆蓋率 35.5%",
      "market_home_prob": 57.6,
      "market_away_prob": 42.4,
      "home_team": "Milwaukee Brewers",
      "away_team": "San Francisco Giants",
      "home_short": "Brewers",
      "away_short": "Giants"
    }
  },
  "9fc40cd3ea77063176a73e678395da73": {
    "pushed_date": "2026-06-04",
    "pre_pushed": true,
    "sim_result": {
      "home_win_pct": 44.9,
      "away_win_pct": 44.4,
      "draw_pct": null,
      "over_pct": 47.7,
      "under_pct": 52.3,
      "home_cover_pct": 44.9,
      "spread_line": -0.537,
      "total_line": 8.286,
      "top5_scores": [
        [
          4,
          4,
          2.5
        ],
        [
          5,
          4,
          2.4
        ],
        [
          4,
          5,
          2.4
        ],
        [
          4,
          3,
          2.3
        ],
        [
          3,
          4,
          2.3
        ]
      ],
      "home_mean": 4.2,
      "away_mean": 4.1,
      "pred_mode": "📐 規則模擬",
      "error": null,
      "has_value": false,
      "value_team": "",
      "value_edge": -4.1,
      "home_edge": -6.5,
      "away_edge": -4.1,
      "kelly_pct": 0.0,
      "confidence": "🟢 高",
      "spread_line_txt": "Cardinals +0.537｜覆蓋率 44.9%",
      "market_home_prob": 51.4,
      "market_away_prob": 48.5,
      "home_team": "St. Louis Cardinals",
      "away_team": "Texas Rangers",
      "home_short": "Cardinals",
      "away_short": "Rangers"
    }
  },
  "54b22c486dccf3bc503a2b33ec17f157": {
    "pushed_date": "2026-06-04",
    "pre_pushed": true,
    "sim_result": {
      "home_win_pct": 43.9,
      "away_win_pct": 45.3,
      "draw_pct": null,
      "over_pct": 48.2,
      "under_pct": 51.8,
      "home_cover_pct": 43.9,
      "spread_line": -0.981,
      "total_line": 8.339,
      "top5_scores": [
        [
          4,
          4,
          2.5
        ],
        [
          4,
          5,
          2.4
        ],
        [
          5,
          4,
          2.3
        ],
        [
          3,
          4,
          2.3
        ],
        [
          4,
          3,
          2.3
        ]
      ],
      "home_mean": 4.1,
      "away_mean": 4.2,
      "pred_mode": "📐 規則模擬",
      "error": null,
      "has_value": false,
      "value_team": "",
      "value_edge": -1.9,
      "home_edge": -1.9,
      "away_edge": -8.9,
      "kelly_pct": 0.0,
      "confidence": "🟢 高",
      "spread_line_txt": "Cubs +0.981｜覆蓋率 43.9%",
      "market_home_prob": 45.8,
      "market_away_prob": 54.2,
      "home_team": "Chicago Cubs",
      "away_team": "Athletics",
      "home_short": "Cubs",
      "away_short": "Athletics"
    }
  },
  "0823b4e80b16060db3aba85b41348d18": {
    "pushed_date": "2026-06-04",
    "pre_pushed": true,
    "sim_result": {
      "home_win_pct": 43.2,
      "away_win_pct": 46.1,
      "draw_pct": null,
      "over_pct": 47.4,
      "under_pct": 52.6,
      "home_cover_pct": 64.4,
      "spread_line": 1.722,
      "total_line": 8.268,
      "top5_scores": [
        [
          4,
          4,
          2.5
        ],
        [
          4,
          5,
          2.4
        ],
        [
          5,
          4,
          2.4
        ],
        [
          3,
          4,
          2.3
        ],
        [
          4,
          3,
          2.2
        ]
      ],
      "home_mean": 4.1,
      "away_mean": 4.2,
      "pred_mode": "📐 規則模擬",
      "error": null,
      "has_value": false,
      "value_team": "",
      "value_edge": 1.6,
      "home_edge": 1.6,
      "away_edge": -12.2,
      "kelly_pct": 0.0,
      "confidence": "🟢 高",
      "spread_line_txt": "Astros -1.722｜覆蓋率 64.4%",
      "market_home_prob": 41.6,
      "market_away_prob": 58.4,
      "home_team": "Houston Astros",
      "away_team": "Pittsburgh Pirates",
      "home_short": "Astros",
      "away_short": "Pirates"
    }
  },
  "1aae688472781f1a1aaf3efdb38e884b": {
    "pushed_date": "2026-06-04",
    "pre_pushed": true,
    "sim_result": {
      "home_win_pct": 39.6,
      "away_win_pct": 58.2,
      "draw_pct": null,
      "over_pct": 51.2,
      "under_pct": 48.8,
      "home_cover_pct": 29.4,
      "spread_line": -5.341,
      "total_line": 218.966,
      "top5_scores": [
        [
          108,
          112,
          0.1
        ],
        [
          110,
          112,
          0.1
        ],
        [
          108,
          109,
          0.1
        ],
        [
          108,
          111,
          0.1
        ],
        [
          107,
          112,
          0.1
        ]
      ],
      "home_mean": 107.4,
      "away_mean": 111.6,
      "pred_mode": "📐 規則模擬",
      "error": null,
      "has_value": false,
      "value_team": "",
      "value_edge": 2.5,
      "home_edge": 2.5,
      "away_edge": -4.7,
      "kelly_pct": 31.8,
      "confidence": "🟡 中",
      "spread_line_txt": "Spurs +5.341｜覆蓋率 29.4%",
      "market_home_prob": 37.1,
      "market_away_prob": 62.9,
      "home_team": "San Antonio Spurs",
      "away_team": "New York Knicks",
      "home_short": "Spurs",
      "away_short": "Knicks"
    }
  },
  "fef20c017b9718b5324615b7ba93f173": {
    "pushed_date": "2026-06-04",
    "pre_pushed": true,
    "sim_result": {
      "home_win_pct": 43.1,
      "away_win_pct": 46.2,
      "draw_pct": null,
      "over_pct": 53.7,
      "under_pct": 46.3,
      "home_cover_pct": 32.9,
      "spread_line": -1.019,
      "total_line": 8.786,
      "top5_scores": [
        [
          4,
          5,
          2.5
        ],
        [
          4,
          4,
          2.5
        ],
        [
          5,
          4,
          2.4
        ],
        [
          5,
          5,
          2.4
        ],
        [
          3,
          5,
          2.2
        ]
      ],
      "home_mean": 4.3,
      "away_mean": 4.5,
      "pred_mode": "📐 規則模擬",
      "error": null,
      "has_value": false,
      "value_team": "",
      "value_edge": 1.4,
      "home_edge": 1.4,
      "away_edge": -12.1,
      "kelly_pct": 4.8,
      "confidence": "🟢 高",
      "spread_line_txt": "Angels +1.019｜覆蓋率 32.9%",
      "market_home_prob": 41.7,
      "market_away_prob": 58.3,
      "home_team": "Los Angeles Angels",
      "away_team": "Colorado Rockies",
      "home_short": "Angels",
      "away_short": "Rockies"
    }
  },
  "f8b638ebe3a01e645658b4699fd18198": {
    "pushed_date": "2026-06-04",
    "pre_pushed": true,
    "sim_result": {
      "home_win_pct": 42.0,
      "away_win_pct": 47.4,
      "draw_pct": null,
      "over_pct": 47.5,
      "under_pct": 52.5,
      "home_cover_pct": 63.1,
      "spread_line": 1.269,
      "total_line": 9.296,
      "top5_scores": [
        [
          4,
          5,
          2.5
        ],
        [
          5,
          5,
          2.5
        ],
        [
          5,
          4,
          2.4
        ],
        [
          4,
          4,
          2.3
        ],
        [
          4,
          6,
          2.2
        ]
      ],
      "home_mean": 4.5,
      "away_mean": 4.8,
      "pred_mode": "📐 規則模擬",
      "error": null,
      "has_value": true,
      "value_team": "home",
      "value_edge": 5.5,
      "home_edge": 5.5,
      "away_edge": -16.1,
      "kelly_pct": 6.3,
      "confidence": "🟢 高",
      "spread_line_txt": "Diamondbacks -1.269｜覆蓋率 63.1%",
      "market_home_prob": 36.5,
      "market_away_prob": 63.5,
      "home_team": "Arizona Diamondbacks",
      "away_team": "Los Angeles Dodgers",
      "home_short": "Diamondbacks",
      "away_short": "Dodgers"
    }
  }
}